{
  "session_id": "omx-1774730361260-nd88u5",
  "started_at": "2026-03-28T20:39:21.281Z",
  "cwd": "/home/justin/ralphton",
  "pid": 2087671,
  "platform": "linux",
  "pid_start_ticks": 37221539,
  "pid_cmdline": "node /home/justin/ralphton/bin/omx ralph --dangerously-bypass-approvals-and-sandbox Execute the MoltScience PRD at .omx/plans/prd-moltscience.md. Read AGENTS.md first, then follow the PRD phases. Elapsed so far: 75 minutes. You have 95 minutes remaining. Current phase hint: Phase 2 (RESEARCH, 207 experiments so far). Check time in the PRD and commit checkpoints on schedule. Use .venv/bin/python (not python) for all Python commands. Flask is already installed. If you hit a content filter error, skip the current step and move to the next phase."
}